ipsw/__init__.py
ipsw/_version.py
ipsw/client.py
ipsw/constants.py
ipsw/errors.py
ipsw/version.py
ipsw/api/__init__.py
ipsw/api/client.py
ipsw/api/daemon.py
ipsw/api/dsc.py
ipsw/api/info.py
ipsw/api/macho.py
ipsw/models/__init__.py
ipsw/models/configs.py
ipsw/models/dsc.py
ipsw/models/info.py
ipsw/models/macho.py
ipsw/models/resource.py
ipsw/transport/__init__.py
ipsw/transport/basehttpadapter.py
ipsw/transport/npipeconn.py
ipsw/transport/npipesocket.py
ipsw/transport/sshconn.py
ipsw/transport/unixconn.py
ipsw/types/__init__.py
ipsw/types/daemon.py
ipsw/utils/__init__.py
ipsw/utils/config.py
ipsw/utils/decorators.py
ipsw/utils/json_stream.py
ipsw/utils/proxy.py
ipsw/utils/socket.py
ipsw/utils/utils.py
ipsw-0.1.4.dist-info/LICENSE
ipsw-0.1.4.dist-info/METADATA
ipsw-0.1.4.dist-info/WHEEL
ipsw-0.1.4.dist-info/top_level.txt
ipsw-0.1.4.dist-info/RECORD
