Metadata-Version: 2.1
Name: ipsw
Version: 0.1.4
Summary: A Python library for the ipsw Engine API.
Home-page: https://github.com/blacktop/ipsw-py
Maintainer: Blacktop
License: MIT
Project-URL: Documentation, https://ipsw-py.readthedocs.io
Project-URL: Changelog, https://ipsw-py.readthedocs.io/en/stable/change-log.html
Project-URL: Source, https://github.com/blacktop/ipsw-py
Project-URL: Tracker, https://github.com/blacktop/ipsw-py/issues
Classifier: Development Status :: 5 - Production/Stable
Classifier: Environment :: Other Environment
Classifier: Intended Audience :: Developers
Classifier: Operating System :: OS Independent
Classifier: Programming Language :: Python
Classifier: Programming Language :: Python :: 3
Classifier: Programming Language :: Python :: 3.7
Classifier: Programming Language :: Python :: 3.8
Classifier: Programming Language :: Python :: 3.9
Classifier: Programming Language :: Python :: 3.10
Classifier: Programming Language :: Python :: 3.11
Classifier: Topic :: Software Development
Classifier: Topic :: Utilities
Classifier: License :: OSI Approved :: Apache Software License
Requires-Python: >=3.7
License-File: LICENSE
Requires-Dist: packaging (>=23.0)
Requires-Dist: requests (>=2.28.2)
Requires-Dist: urllib3 (>=1.26.15)
Requires-Dist: websocket-client (>=1.5.1)
Requires-Dist: pyyaml (>=6.0)
Requires-Dist: pywin32 (>=306) ; sys_platform == "win32"
Provides-Extra: ssh
Requires-Dist: paramiko (>=3.1.0) ; extra == 'ssh'
Provides-Extra: tls
